tests/__init__.py
tests/conftest.py
tests/test_parsing.py
tests/test_vectorstores.py
tests/test_wdoc.py
wdoc/__init__.py
wdoc/__main__.py
wdoc/wdoc.py
wdoc/docs/examples.md
wdoc/docs/help.md
wdoc/docs/parse_doc_help.md
wdoc/utils/__init__.py
wdoc/utils/batch_file_loader.py
wdoc/utils/embeddings.py
wdoc/utils/env.py
wdoc/utils/errors.py
wdoc/utils/filters.py
wdoc/utils/interact.py
wdoc/utils/llm.py
wdoc/utils/load_recursive.py
wdoc/utils/logger.py
wdoc/utils/misc.py
wdoc/utils/prompts.py
wdoc/utils/retrievers.py
wdoc/utils/customs/__init__.py
wdoc/utils/customs/binary_faiss_vectorstore.py
wdoc/utils/customs/compressed_embeddings_cacher.py
wdoc/utils/customs/fix_llm_caching.py
wdoc/utils/customs/litellm_embeddings.py
wdoc/utils/loaders/__init__.py
wdoc/utils/loaders/anki.py
wdoc/utils/loaders/epub.py
wdoc/utils/loaders/json_dict.py
wdoc/utils/loaders/local_audio.py
wdoc/utils/loaders/local_html.py
wdoc/utils/loaders/local_video.py
wdoc/utils/loaders/logseq_markdown.py
wdoc/utils/loaders/online_media.py
wdoc/utils/loaders/online_pdf.py
wdoc/utils/loaders/pdf.py
wdoc/utils/loaders/powerpoint.py
wdoc/utils/loaders/shared.py
wdoc/utils/loaders/shared_audio.py
wdoc/utils/loaders/string.py
wdoc/utils/loaders/text.py
wdoc/utils/loaders/txt.py
wdoc/utils/loaders/url.py
wdoc/utils/loaders/word.py
wdoc/utils/loaders/youtube.py
wdoc/utils/tasks/__init__.py
wdoc/utils/tasks/parse.py
wdoc/utils/tasks/query.py
wdoc/utils/tasks/search.py
wdoc/utils/tasks/shared_query_search.py
wdoc/utils/tasks/summarize.py
wdoc/utils/tasks/types.py
wdoc-5.0.0.dist-info/licenses/LICENSE
wdoc-5.0.0.dist-info/METADATA
wdoc-5.0.0.dist-info/WHEEL
wdoc-5.0.0.dist-info/entry_points.txt
wdoc-5.0.0.dist-info/top_level.txt
wdoc-5.0.0.dist-info/RECORD
