Metadata-Version: 2.4
Name: wdoc
Version: 5.0.0
Summary: A perfect AI powered RAG for document query and summary. Supports ~all LLM and ~all filetypes (url, pdf, epub, youtube (incl playlist), audio, anki, md, docx, pptx, oe any combination!)
Home-page: https://github.com/thiswillbeyourgithub/wdoc/
License: AGPLv3
Keywords: RAG,search,summary,summarize,pdf,documents,doc,docx,youtube,mp3,embeddings,AI,LLM,openai,logseq,doctools,doctoolsllm,winston_doc
Classifier: Programming Language :: Python :: 3
Classifier: Operating System :: OS Independent
Requires-Python: >=3.11
License-File: LICENSE
Requires-Dist: sqlalchemy>=2.0.32
Requires-Dist: beautifulsoup4>=4.12.3
Requires-Dist: fire>=0.6.0
Requires-Dist: ftfy>=6.2.0
Requires-Dist: joblib>=1.4.2
Requires-Dist: langchain>=1.2.0
Requires-Dist: langchain-classic>=1.0.0
Requires-Dist: langchain-community>=0.3.30
Requires-Dist: langchain-openai>=0.3.34
Requires-Dist: langchain-litellm>=0.3.5
Requires-Dist: langfuse>=3.6.1
Requires-Dist: litellm>=v1.78.2
Requires-Dist: nest_asyncio>=1.6.0
Requires-Dist: chonkie[all]>=1.4.0
Requires-Dist: chonkie[semantic]>=1.4.0
Requires-Dist: prompt-toolkit>=3.0.47
Requires-Dist: tqdm>=4.66.4
Requires-Dist: faiss-cpu>=1.8.0
Requires-Dist: rich>=13.8.1
Requires-Dist: beartype>=0.22.2
Requires-Dist: platformdirs>=4.2.2
Requires-Dist: dill>=0.3.8
Requires-Dist: pyfiglet>=1.0.2
Requires-Dist: rtoml>=0.11.0
Requires-Dist: loguru>=0.7.2
Requires-Dist: grandalf>=0.8
Requires-Dist: lazy-import>=0.2.2
Requires-Dist: py_ankiconnect>=1.1.2
Requires-Dist: scikit-learn>=1.5.1
Requires-Dist: scipy>=1.13.1
Requires-Dist: uuid6>=2025.0.1
Requires-Dist: PersistDict>=0.2.14
Requires-Dist: nltk>=3.9.2
Requires-Dist: blake3>=1.0.8
Requires-Dist: pandas>=2.3.3
Requires-Dist: playwright>=1.45.0
Requires-Dist: openparse[ml]>=0.5.7
Requires-Dist: yt-dlp>=2025.09.26
Requires-Dist: youtube-transcript-api>=0.6.2
Requires-Dist: tldextract>=5.1.2
Requires-Dist: goose3>=3.1.20
Requires-Dist: ddgs>=9.6.0
Requires-Dist: duckduckgo-search>=8.1.1
Requires-Dist: deepgram-sdk>=3.2.7
Requires-Dist: httpx>=0.27.0
Requires-Dist: pydub>=0.25.1
Requires-Dist: ffmpeg-python>=0.2.0
Requires-Dist: torchaudio>=2.8.0
Requires-Dist: trio>=0.31.0
Requires-Dist: unstructured[all-docs]>=0.18.15
Provides-Extra: full
Requires-Dist: pdfminer.six>=20231228; extra == "full"
Requires-Dist: pillow_heif>=0.16.0; extra == "full"
Requires-Dist: pypdfium2>=4.30.0; extra == "full"
Requires-Dist: pymupdf>=1.24.5; extra == "full"
Requires-Dist: pdfplumber>=0.11.1; extra == "full"
Requires-Dist: pdf2image>=1.17.0; extra == "full"
Requires-Dist: docx2txt>=0.8; extra == "full"
Requires-Dist: pandoc>=2.4; extra == "full"
Requires-Dist: ankipandas>=0.3.15; extra == "full"
Requires-Dist: LogseqMarkdownParser>=3.3; extra == "full"
Provides-Extra: fasttext
Requires-Dist: fasttext-langdetect>=1.0.5; extra == "fasttext"
Requires-Dist: langdetect>=1.0.9; extra == "fasttext"
Provides-Extra: pdftotext
Requires-Dist: pdftotext>=2.2.2; extra == "pdftotext"
Provides-Extra: dev
Requires-Dist: ruff>=0.14.1; extra == "dev"
Requires-Dist: pre-commit>=4.1.0; extra == "dev"
Requires-Dist: pytest>=8.3.4; extra == "dev"
Requires-Dist: pytest-xdist>=3.6.1; extra == "dev"
Requires-Dist: build>=1.2.2.post1; extra == "dev"
Requires-Dist: twine>=6.1.0; extra == "dev"
Requires-Dist: bumpver>=2025.1131; extra == "dev"
Dynamic: classifier
Dynamic: description
Dynamic: description-content-type
Dynamic: home-page
Dynamic: keywords
Dynamic: license
Dynamic: license-file
Dynamic: provides-extra
Dynamic: requires-dist
Dynamic: requires-python
Dynamic: summary
